Workbook

Sheet README
A1: Mondeto tokenomics v2 — sharded identical maps, natural demand cap
A2: Lena · DevRel Lead, Celo Core Co · May 15, 2026
A4: WHAT CHANGED FROM v1
A5: - No contract change. The ~$7 (hard ~$10) ceiling is a NATURAL demand cap, not coded - buyers skip a pixel once it gets that pricey.
A6: - No country maps, no Self Protocol gating. Several identical 170x100 world maps. Users free-pick from a list.
A7: - Fee math corrected: v1 used $50/pixel (whale WtP). At a $7 natural cap the average sale is ~$1, so revenue is ~10x lower.
A9: THE MECHANIC, STATED PRECISELY
A10: - Sale #n costs initialPrice x 2^(n-1). Sale 1 = $0.003, sale 12 = $6.14, sale 13 = $12.29 (over $10 -> demand stops).
A11: - A pixel takes ~12 sales to climb from $0.003 to its natural cap. That is one CYCLE.
A12: - Volume per cycle is FIXED: 0.003 x (2^12 - 1) = $12.29, regardless of how fast it happens.
A13: - After the cap the pixel is dormant. Halving (30-day half-life) is the ONLY thing that makes it buyable again.
A15: THE KEY FINDING
... A26: 6. Summary - the recommendation.

Sheet Inputs
A1: Inputs & Assumptions
A3: CONTRACT (fixed - no changes)
A4: Initial pixel price (USDT) | B4: 0.003 | C4: Sale 1 price. Doubles each subsequent sale.
A5: Halving half-life (days) | B5: 30 | C5: Price halves every 30 days unsold. KEY LEVER.
A6: Map width (cells) | B6: 170 | C6: Fixed - cannot change per your constraint.
A7: Map height (cells) | B7: 100 | C7: Fixed.
A8: Land fraction | B8: 0.7 | C8: ~70% of grid sellable (water excluded).
A10: NATURAL DEMAND CAP
A11: Natural cap - soft ($) | B11: 7 | C11: Most buyers walk away above this.
A12: Natural cap - hard ($) | B12: 10 | C12: Almost nobody pays above this.
A14: DEMAND
A15: Target DAU | B15: 100000 | C15: App daily actives (most just look).
A16: Share of DAU who BUY daily | B16: 0.05 | C16: THE big unknown. See Revenue_Grid for full range.
A17: Pixels bought per buyer per day | B17: 2 | C17: Among users who do buy.
A18: Day-1 launch users | B18: 100000 | C18: Launch-spike stress test.
A19: Day-1 pixels attempted per user | B19: 3 | C19: Bidding pressure on day 1.
A20: Hotspot unevenness factor | B20: 2.5 | C20: Demand clusters on good spots, not uniform. >=1.
A22: POLICY LEVERS
A23: Fee rate (bps) | B23: 500 | C23: 500 = 5%. Launch here; 700 (7%) is the upper lever.
A24: Number of maps deployed | B24: 6 | C24: Identical 170x100 maps. Each = a separate contract deploy.
A25: Marketing budget ($/mo) | B25: 15000 | C25: Recurring spend to be covered by fees.

Sheet Cycle_Economics
A1: Cycle economics - the fixed per-pixel math
A2: A 'cycle' = a pixel climbing from $0.003 to its natural cap. Volume per cycle is fixed.
A4: Sales to reach soft cap (~$7) | B4: =FLOOR(LOG(Inputs!$B$11/Inputs!$B$4,2),1)+1 -> 12 | C4: 0.003 x 2^(n-1) <= 7
A5: Sales to reach hard cap (~$10) | B5: =FLOOR(LOG(Inputs!$B$12/Inputs!$B$4,2),1)+1 -> 12 | C5: 0.003 x 2^(n-1) <= 10
A6: Sales counted per cycle | B6: =B4 -> 12 | C6: Use the soft cap - where demand really stops
A7: Price at last sale of cycle ($) | B7: =Inputs!$B$4*2^(B6-1) -> 6.144 | C7: Final, most expensive sale
A8: VOLUME PER CYCLE ($) | B8: =Inputs!$B$4*(2^B6-1) -> 12.285 | C8: Geometric sum 0.003 x (2^n - 1). FIXED.
A9: Avg sale price in a cycle ($) | B9: =B8/B6 -> 1.02375 | C9: Cycle volume / sales. ~$1 - the real number.
A10: Fee per cycle @ current rate ($) | B10: =B8*(Inputs!$B$23/10000) -> 0.61425 | C10: Platform earnings per completed cycle
A11: Map land pixels (per map) | B11: =Inputs!$B$6*Inputs!$B$7*Inputs!$B$8 -> 11900 | C11: Fixed map capacity
A12: Total pixels (all maps) | B12: =B11*Inputs!$B$24 -> 71400 | C12: Across all deployed maps
A13: Max volume if every pixel cycles once ($) | B13: =B8*B12 -> 877149 | C13: One full sweep of all maps
A14: fees from one full sweep ($) | B14: =B13*(Inputs!$B$23/10000) -> 43857.45 | C14: One-time-ish; then halving bottleneck

Sheet Halving_Bottleneck
A1: The halving bottleneck - why maps go dormant
A2: After a pixel hits the cap, only halving makes it cheap again. At 30-day half-life that is slow.
A4: Price at cap ($) | B4: =Inputs!$B$4*2^(Cycle_Economics!$B$6-1) -> 6.144 | C4: Where the pixel parks
A5: 'Attractive again' price ($) | B5: 0.1 | C5: Price at which buyers re-engage (tunable)
A6: Halvings needed to recover | B6: =LOG(B4/B5,2) -> 5.9411063 | C6: log2(cap / attractive)
A7: Recovery time (days) | B7: =B6*Inputs!$B$5 -> 178.23319 | C7: Halvings x half-life - the dormant stretch
A8: Full cycle length (days) | B8: =B7 -> 178.23319 | C8: Recovery dominates; ramp-up is fast
A9: Cycles per pixel per month | B9: =30/B8 -> 0.16831882 | C9: 30 / cycle length
A10: Sustainable cycles/map/month | B10: =Cycle_Economics!$B$11*B9 -> 2002.994 | C10: Pixels x cycles each
A11: Sustainable fees/map/month ($) | B11: =B10*Cycle_Economics!$B$8*(Inputs!$B$23/10000) -> 1230.339 | C11: Mature-map steady state
A14: SENSITIVITY - halving half-life vs sustainable fees per map per month
A16: Halving half-life (days) | B16: 7 | C16: 14 | D16: 21 | E16: 30 | F16: 45 | G16: 60
A17: Sustainable fees/map/month ($) | B17: =Cycle_Economics!$B$11*(30/(LOG(B4/B5,2)*7))*Cycle_Economics!$B$8*(Inputs!$B$23/10000) -> 5272.8816 | C17: =Cycle_Economics!$B$11*(30/(LOG(B4/B5,2)*14))*Cycle_Economics!$B$8*(Inputs!$B$23/10000) -> 2636.4408 | D17: =Cycle_Economics!$B$11*(30/(LOG(B4/B5,2)*21))*Cycle_Economics!$B$8*(Inputs!$B$23/10000) -> 1757.6272 | E17: =Cycle_Economics!$B$11*(30/(LOG(B4/B5,2)*30))*Cycle_Economics!$B$8*(Inputs!$B$23/10000) -> 1230.339 | F17: =Cycle_Economics!$B$11*(30/(LOG(B4/B5,2)*45))*Cycle_Economics!$B$8*(Inputs!$B$23/10000) -> 820.22602 | G17: =Cycle_Economics!$B$11*(30/(LOG(B4/B5,2)*60))*Cycle_Economics!$B$8*(Inputs!$B$23/10000) -> 615.16952
A19: Read: halving the half-life roughly doubles sustainable revenue per map (faster recycling).

Sheet Revenue_Grid
A1: Revenue grid - monthly fees vs buyer share x number of maps
A2: Demand-driven, capped by map supply. Green = covers $15k/mo. Fee rate from Inputs (5%).
A4: Monthly purchases = DAU x buyer share x pixels/buyer x 30
A5: Monthly fees = MIN(demand cycles, supply cycles) x volume-per-cycle x fee rate
A7: Buyer share v / # maps > | B7: 2 | C7: 4 | D7: 6 | E7: 8 | F7: 10 | G7: 15 | H7: 20
A8: 0.5% of DAU | B8: =MIN((Inputs!$B$15*0.005*Inputs!$B$17*30)/Cycle_Economics!$B$6,Cycle_Economics!$B$11*2*Halving_Bottleneck!$B$9)*Cycle_Economics!$B$8*(Inputs!$B$23/10000) -> 1535.625 | C8: =MIN((Inputs!$B$15*0.005*Inputs!$B$17*30)/Cycle_Economics!$B$6,Cycle_Economics!$B$11*4*Halving_Bottleneck!$B$9)*Cycle_Economics!$B$8*(Inputs!$B$23/10000) -> 1535.625 | D8: =MIN((Inputs!$B$15*0.005*Inputs!$B$17*30)/Cycle_Economics!$B$6,Cycle_Economics!$B$11*6*Halving_Bottleneck!$B$9)*Cycle_Economics!$B$8*(Inputs!$B$23/10000) -> 1535.625 | E8: =MIN((Inputs!$B$15*0.005*Inputs!$B$17*30)/Cycle_Economics!$B$6,Cycle_Economics!$B$11*8*Halving_Bottleneck!$B$9)*Cycle_Economics!$B$8*(Inputs!$B$23/10000) -> 1535.625 | F8: =MIN((Inputs!$B$15*0.005*Inputs!$B$17*30)/Cycle_Economics!$B$6,Cycle_Economics!$B$11*10*Halving_Bottleneck!$B$9)*Cycle_Economics!$B$8*(Inputs!$B$23/10000) -> 1535.625 | G8: =MIN((Inputs!$B$15*0.005*Inputs!$B$17*30)/Cycle_Economics!$B$6,Cycle_Economics!$B$11*15*Halving_Bottleneck!$B$9)*Cycle_Economics!$B$8*(Inputs!$B$23/10000) -> 1535.625 | H8: =MIN((Inputs!$B$15*0.005*Inputs!$B$17*30)/Cycle_Economics!$B$6,Cycle_Economics!$B$11*20*Halving_Bottleneck!$B$9)*Cycle_Economics!$B$8*(Inputs!$B$23/10000) -> 1535.625
A9: 1.0% of DAU | B9: =MIN((Inputs!$B$15*0.01*Inputs!$B$17*30)/Cycle_Economics!$B$6,Cycle_Economics!$B$11*2*Halving_Bottleneck!$B$9)*Cycle_Economics!$B$8*(Inputs!$B$23/10000) -> 2460.6781 | C9: =MIN((Inputs!$B$15*0.01*Inputs!$B$17*30)/Cycle_Economics!$B$6,Cycle_Economics!$B$11*4*Halving_Bottleneck!$B$9)*Cycle_Economics!$B$8*(Inputs!$B$23/10000) -> 3071.25 | D9: =MIN((Inputs!$B$15*0.01*Inputs!$B$17*30)/Cycle_Economics!$B$6,Cycle_Economics!$B$11*6*Halving_Bottleneck!$B$9)*Cycle_Economics!$B$8*(Inputs!$B$23/10000) -> 3071.25 | E9: =MIN((Inputs!$B$15*0.01*Inputs!$B$17*30)/Cycle_Economics!$B$6,Cycle_Economics!$B$11*8*Halving_Bottleneck!$B$9)*Cycle_Economics!$B$8*(Inputs!$B$23/10000) -> 3071.25 | F9: =MIN((Inputs!$B$15*0.01*Inputs!$B$17*30)/Cycle_Economics!$B$6,Cycle_Economics!$B$11*10*Halving_Bottleneck!$B$9)*Cycle_Economics!$B$8*(Inputs!$B$23/10000) -> 3071.25 | G9: =MIN((Inputs!$B$15*0.01*Inputs!$B$17*30)/Cycle_Economics!$B$6,Cycle_Economics!$B$11*15*Halving_Bottleneck!$B$9)*Cycle_Economics!$B$8*(Inputs!$B$23/10000) -> 3071.25 | H9: =MIN((Inputs!$B$15*0.01*Inputs!$B$17*30)/Cycle_Economics!$B$6,Cycle_Economics!$B$11*20*Halving_Bottleneck!$B$9)*Cycle_Economics!$B$8*(Inputs!$B$23/10000) -> 3071.25
A10: 2.0% of DAU | B10: =MIN((Inputs!$B$15*0.02*Inputs!$B$17*30)/Cycle_Economics!$B$6,Cycle_Economics!$B$11*2*Halving_Bottleneck!$B$9)*Cycle_Economics!$B$8*(Inputs!$B$23/10000) -> 2460.6781 | C10: =MIN((Inputs!$B$15*0.02*Inputs!$B$17*30)/Cycle_Economics!$B$6,Cycle_Economics!$B$11*4*Halving_Bottleneck!$B$9)*Cycle_Economics!$B$8*(Inputs!$B$23/10000) -> 4921.3561 | D10: =MIN((Inputs!$B$15*0.02*Inputs!$B$17*30)/Cycle_Economics!$B$6,Cycle_Economics!$B$11*6*Halving_Bottleneck!$B$9)*Cycle_Economics!$B$8*(Inputs!$B$23/10000) -> 6142.5 | E10: =MIN((Inputs!$B$15*0.02*Inputs!$B$17*30)/Cycle_Economics!$B$6,Cycle_Economics!$B$11*8*Halving_Bottleneck!$B$9)*Cycle_Economics!$B$8*(Inputs!$B$23/10000) -> 6142.5 | F10: =MIN((Inputs!$B$15*0.02*Inputs!$B$17*30)/Cycle_Economics!$B$6,Cycle_Economics!$B$11*10*Halving_Bottleneck!$B$9)*Cycle_Economics!$B$8*(Inputs!$B$23/10000) -> 6142.5 | G10: =MIN((Inputs!$B$15*0.02*Inputs!$B$17*30)/Cycle_Economics!$B$6,Cycle_Economics!$B$11*15*Halving_Bottleneck!$B$9)*Cycle_Economics!$B$8*(Inputs!$B$23/10000) -> 6142.5 | H10: =MIN((Inputs!$B$15*0.02*Inputs!$B$17*30)/Cycle_Economics!$B$6,Cycle_Economics!$B$11*20*Halving_Bottleneck!$B$9)*Cycle_Economics!$B$8*(Inputs!$B$23/10000) -> 6142.5
A11: 3.0% of DAU | B11: =MIN((Inputs!$B$15*0.03*Inputs!$B$17*30)/Cycle_Economics!$B$6,Cycle_Economics!$B$11*2*Halving_Bottleneck!$B$9)*Cycle_Economics!$B$8*(Inputs!$B$23/10000) -> 2460.6781 | C11: =MIN((Inputs!$B$15*0.03*Inputs!$B$17*30)/Cycle_Economics!$B$6,Cycle_Economics!$B$11*4*Halving_Bottleneck!$B$9)*Cycle_Economics!$B$8*(Inputs!$B$23/10000) -> 4921.3561 | D11: =MIN((Inputs!$B$15*0.03*Inputs!$B$17*30)/Cycle_Economics!$B$6,Cycle_Economics!$B$11*6*Halving_Bottleneck!$B$9)*Cycle_Economics!$B$8*(Inputs!$B$23/10000) -> 7382.0342 | E11: =MIN((Inputs!$B$15*0.03*Inputs!$B$17*30)/Cycle_Economics!$B$6,Cycle_Economics!$B$11*8*Halving_Bottleneck!$B$9)*Cycle_Economics!$B$8*(Inputs!$B$23/10000) -> 9213.75 | F11: =MIN((Inputs!$B$15*0.03*Inputs!$B$17*30)/Cycle_Economics!$B$6,Cycle_Economics!$B$11*10*Halving_Bottleneck!$B$9)*Cycle_Economics!$B$8*(Inputs!$B$23/10000) -> 9213.75 | G11: =MIN((Inputs!$B$15*0.03*Inputs!$B$17*30)/Cycle_Economics!$B$6,Cycle_Economics!$B$11*15*Halving_Bottleneck!$B$9)*Cycle_Economics!$B$8*(Inputs!$B$23/10000) -> 9213.75 | H11: =MIN((Inputs!$B$15*0.03*Inputs!$B$17*30)/Cycle_Economics!$B$6,Cycle_Economics!$B$11*20*Halving_Bottleneck!$B$9)*Cycle_Economics!$B$8*(Inputs!$B$23/10000) -> 9213.75
A12: 5.0% of DAU | B12: =MIN((Inputs!$B$15*0.05*Inputs!$B$17*30)/Cycle_Economics!$B$6,Cycle_Economics!$B$11*2*Halving_Bottleneck!$B$9)*Cycle_Economics!$B$8*(Inputs!$B$23/10000) -> 2460.6781 | C12: =MIN((Inputs!$B$15*0.05*Inputs!$B$17*30)/Cycle_Economics!$B$6,Cycle_Economics!$B$11*4*Halving_Bottleneck!$B$9)*Cycle_Economics!$B$8*(Inputs!$B$23/10000) -> 4921.3561 | D12: =MIN((Inputs!$B$15*0.05*Inputs!$B$17*30)/Cycle_Economics!$B$6,Cycle_Economics!$B$11*6*Halving_Bottleneck!$B$9)*Cycle_Economics!$B$8*(Inputs!$B$23/10000) -> 7382.0342 | E12: =MIN((Inputs!$B$15*0.05*Inputs!$B$17*30)/Cycle_Economics!$B$6,Cycle_Economics!$B$11*8*Halving_Bottleneck!$B$9)*Cycle_Economics!$B$8*(Inputs!$B$23/10000) -> 9842.7123 | F12: =MIN((Inputs!$B$15*0.05*Inputs!$B$17*30)/Cycle_Economics!$B$6,Cycle_Economics!$B$11*10*Halving_Bottleneck!$B$9)*Cycle_Economics!$B$8*(Inputs!$B$23/10000) -> 12303.39 | G12: =MIN((Inputs!$B$15*0.05*Inputs!$B$17*30)/Cycle_Economics!$B$6,Cycle_Economics!$B$11*15*Halving_Bottleneck!$B$9)*Cycle_Economics!$B$8*(Inputs!$B$23/10000) -> 15356.25 | H12: =MIN((Inputs!$B$15*0.05*Inputs!$B$17*30)/Cycle_Economics!$B$6,Cycle_Economics!$B$11*20*Halving_Bottleneck!$B$9)*Cycle_Economics!$B$8*(Inputs!$B$23/10000) -> 15356.25
A13: 8.0% of DAU | B13: =MIN((Inputs!$B$15*0.08*Inputs!$B$17*30)/Cycle_Economics!$B$6,Cycle_Economics!$B$11*2*Halving_Bottleneck!$B$9)*Cycle_Economics!$B$8*(Inputs!$B$23/10000) -> 2460.6781 | C13: =MIN((Inputs!$B$15*0.08*Inputs!$B$17*30)/Cycle_Economics!$B$6,Cycle_Economics!$B$11*4*Halving_Bottleneck!$B$9)*Cycle_Economics!$B$8*(Inputs!$B$23/10000) -> 4921.3561 | D13: =MIN((Inputs!$B$15*0.08*Inputs!$B$17*30)/Cycle_Economics!$B$6,Cycle_Economics!$B$11*6*Halving_Bottleneck!$B$9)*Cycle_Economics!$B$8*(Inputs!$B$23/10000) -> 7382.0342 | E13: =MIN((Inputs!$B$15*0.08*Inputs!$B$17*30)/Cycle_Economics!$B$6,Cycle_Economics!$B$11*8*Halving_Bottleneck!$B$9)*Cycle_Economics!$B$8*(Inputs!$B$23/10000) -> 9842.7123 | F13: =MIN((Inputs!$B$15*0.08*Inputs!$B$17*30)/Cycle_Economics!$B$6,Cycle_Economics!$B$11*10*Halving_Bottleneck!$B$9)*Cycle_Economics!$B$8*(Inputs!$B$23/10000) -> 12303.39 | G13: =MIN((Inputs!$B$15*0.08*Inputs!$B$17*30)/Cycle_Economics!$B$6,Cycle_Economics!$B$11*15*Halving_Bottleneck!$B$9)*Cycle_Economics!$B$8*(Inputs!$B$23/10000) -> 18455.086 | H13: =MIN((Inputs!$B$15*0.08*Inputs!$B$17*30)/Cycle_Economics!$B$6,Cycle_Economics!$B$11*20*Halving_Bottleneck!$B$9)*Cycle_Economics!$B$8*(Inputs!$B$23/10000) -> 24570
A14: 10.0% of DAU | B14: =MIN((Inputs!$B$15*0.1*Inputs!$B$17*30)/Cycle_Economics!$B$6,Cycle_Economics!$B$11*2*Halving_Bottleneck!$B$9)*Cycle_Economics!$B$8*(Inputs!$B$23/10000) -> 2460.6781 | C14: =MIN((Inputs!$B$15*0.1*Inputs!$B$17*30)/Cycle_Economics!$B$6,Cycle_Economics!$B$11*4*Halving_Bottleneck!$B$9)*Cycle_Economics!$B$8*(Inputs!$B$23/10000) -> 4921.3561 | D14: =MIN((Inputs!$B$15*0.1*Inputs!$B$17*30)/Cycle_Economics!$B$6,Cycle_Economics!$B$11*6*Halving_Bottleneck!$B$9)*Cycle_Economics!$B$8*(Inputs!$B$23/10000) -> 7382.0342 | E14: =MIN((Inputs!$B$15*0.1*Inputs!$B$17*30)/Cycle_Economics!$B$6,Cycle_Economics!$B$11*8*Halving_Bottleneck!$B$9)*Cycle_Economics!$B$8*(Inputs!$B$23/10000) -> 9842.7123 | F14: =MIN((Inputs!$B$15*0.1*Inputs!$B$17*30)/Cycle_Economics!$B$6,Cycle_Economics!$B$11*10*Halving_Bottleneck!$B$9)*Cycle_Economics!$B$8*(Inputs!$B$23/10000) -> 12303.39 | G14: =MIN((Inputs!$B$15*0.1*Inputs!$B$17*30)/Cycle_Economics!$B$6,Cycle_Economics!$B$11*15*Halving_Bottleneck!$B$9)*Cycle_Economics!$B$8*(Inputs!$B$23/10000) -> 18455.086 | H14: =MIN((Inputs!$B$15*0.1*Inputs!$B$17*30)/Cycle_Economics!$B$6,Cycle_Economics!$B$11*20*Halving_Bottleneck!$B$9)*Cycle_Economics!$B$8*(Inputs!$B$23/10000) -> 24606.781
A17: Where green starts is your answer. A flat low number across the high-map columns means
A18: demand (not capacity) is the limit there - adding maps won't help.

Sheet Launch_Spike
A1: Launch spike - maps needed to survive day 1 under the natural cap
A2: On day 1 all pixels are fresh, so halving is irrelevant - it's pure capacity vs demand.
A4: Day-1 purchase attempts | B4: =Inputs!$B$18*Inputs!$B$19 -> 300000 | C4: Users x pixels each
A5: Cycles those attempts represent | B5: =B4/Cycle_Economics!$B$6 -> 25000 | C5: / sales per cycle
A6: Pixels needed (even spread) | B6: =B5 -> 25000 | C6: 1 cycle ~ 1 pixel maxed on day 1
A7: Pixels needed (with hotspotting) | B7: =B6*Inputs!$B$20 -> 62500 | C7: Demand clusters on good spots
A8: Maps needed for safe launch | B8: =ROUNDUP(B7/Cycle_Economics!$B$11,0) -> 6 | C8: Keeps popular pixels under cap on day 1
A9: Maps currently planned | B9: =Inputs!$B$24 -> 6 | C9: From Inputs
A10: Launch verdict | B10: =IF(Inputs!$B$24>=B8,"OK - spike absorbed","TOO FEW - pixels blow past cap") -> OK - spike absorbed

Sheet Summary
A1: Summary & Recommendations
A3: THE NUMBERS
A4: Sales per pixel per cycle | B4: =Cycle_Economics!$B$6 -> 12 | C4: $0.003 -> ~$6 in ~12 doublings
A5: Volume per cycle ($) | B5: =Cycle_Economics!$B$8 -> 12.285 | C5: FIXED by the doubling math
A6: Avg sale price ($) | B6: =Cycle_Economics!$B$9 -> 1.02375 | C6: Why v1's $50 was wrong - it's ~$1
A7: Pixel recovery time (days) | B7: =Halving_Bottleneck!B7 -> 178.23319 | C7: Dormant stretch after a pixel caps
A8: Sustainable fees/map/mo ($) | B8: =Halving_Bottleneck!$B$11 -> 1230.339 | C8: Mature-map steady state, current settings
A9: Maps to survive 100k launch | B9: =Launch_Spike!$B$8 -> 6 | C9: Day-1 capacity requirement
A10: Marketing budget ($/mo) | B10: =Inputs!$B$25 -> 15000
A12: RECOMMENDATIONS
A13: 1. Keep natural cap | B13: No contract change | C13: Demand dies ~$7. Whoever overpays, their call - internal assumption.
A14: 2. Launch map count | B14: ~6 identical maps | C14: Absorbs the 100k day-1 spike so pixels don't blow past cap on day 1.
A15: 3. Halving period | B15: Shorten 30 -> 14 days | C15: Biggest lever. At 30d maps sleep ~6mo after saturating. 14d ~halves maps needed.
A16: 4. Fee rate | B16: 5% now, 7% as lever | C16: Make feeRate admin-settable (already flagged) so 5->7 is one tx, not a redeploy.
A17: 5. Map deploy cadence | B17: 1-2 new maps / month | C17: Fresh maps = cheap pixels = the only sustained revenue while halving is slow.
A18: 6. User distribution | B18: Free pick + fill meter | C18: Show each map's fill % and live activity; open a new map only when current set saturates.
A19: 7. Initial price | B19: Keep $0.003 | C19: 12 doublings to cap is a good cycle length. Don't touch.
A20: 8. Ground in real data | B20: Pull contract events | C20: Replace 'buyer share' guess with observed buyers/day from the live contract.
